[{
    "red": {
        "name": "tmm",
        "href": "../player/tmm/json",
        "score": 6,
        "skillChange": 5.20695424021,
        "rankChange": 1,
        "newRank": 13
    },
    "blue": {
        "name": "sjs",
        "href": "../player/sjs/json",
        "score": 4,
        "skillChange": -5.20695424021,
        "rankChange": 0,
        "newRank": 10
    },
    "positionSwap": false,
    "date": 1433852883
}, {
  "red" : {
    "name" : "jwl",
    "score" : 5,
    "skillChange" : -2.14233699163
  },
  "blue" : {
    "name" : "sjs",
    "score" : 5,
    "skillChange" : 2.14233699163
  },
  "date" : 1433864657
}]